setup.py
stacklesslib/__init__.py
stacklesslib/app.py
stacklesslib/async.py
stacklesslib/base.py
stacklesslib/errors.py
stacklesslib/events.py
stacklesslib/fittings.py
stacklesslib/futures.py
stacklesslib/locks.py
stacklesslib/magic.py
stacklesslib/main.py
stacklesslib/monkeypatch.py
stacklesslib/socketserver.py
stacklesslib/threadpool.py
stacklesslib/util.py
stacklesslib/wait.py
stacklesslib/weakmethod.py
stacklesslib.egg-info/PKG-INFO
stacklesslib.egg-info/SOURCES.txt
stacklesslib.egg-info/dependency_links.txt
stacklesslib.egg-info/top_level.txt
stacklesslib/replacements/__init__.py
stacklesslib/replacements/greenlet.py
stacklesslib/replacements/popen.py
stacklesslib/replacements/select.py
stacklesslib/replacements/socket.py
stacklesslib/replacements/thread.py
stacklesslib/replacements/threading.py
stacklesslib/test/__init__.py
stacklesslib/test/lock_tests.py
stacklesslib/test/run.py
stacklesslib/test/support.py
stacklesslib/test/test_fittings.py
stacklesslib/test/test_futures.py
stacklesslib/test/test_greenlet.py
stacklesslib/test/test_threadpool.py
stacklesslib/test/test_wait.py
stacklesslib/test/test_weakmethod.py
stacklesslib/test/testasync.py
stacklesslib/test/testlocks.py
stacklesslib/test/testmainloop.py
stacklesslib/test/testpopen.py
stacklesslib/test/teststdlibunittests.py
stacklesslib/test/testtimeout.py
stacklesslib/test/testutil.py