Metadata-Version: 1.0
Name: stacklesslib
Version: 1.2.0
Summary: A set of essential utilities for Stackless
Home-page: https://bitbucket.org/stackless-dev/stacklesslib
Author: Kristján Valur Jónsson
Author-email: sweskman@gmail.com
License: PSF
Keywords: stackless stacklesssocket
Platform: UNKNOWN
